odoo/addons/account_invoice_discount_display_amount/README.rst
odoo/addons/account_invoice_discount_display_amount/__init__.py
odoo/addons/account_invoice_discount_display_amount/__manifest__.py
odoo/addons/account_invoice_discount_display_amount/i18n/account_invoice_discount_display_amount.pot
odoo/addons/account_invoice_discount_display_amount/i18n/es.po
odoo/addons/account_invoice_discount_display_amount/i18n/it.po
odoo/addons/account_invoice_discount_display_amount/models/__init__.py
odoo/addons/account_invoice_discount_display_amount/models/account_move.py
odoo/addons/account_invoice_discount_display_amount/models/account_move_line.py
odoo/addons/account_invoice_discount_display_amount/readme/CONFIGURE.rst
odoo/addons/account_invoice_discount_display_amount/readme/CONTRIBUTORS.rst
odoo/addons/account_invoice_discount_display_amount/readme/DESCRIPTION.rst
odoo/addons/account_invoice_discount_display_amount/readme/USAGE.rst
odoo/addons/account_invoice_discount_display_amount/report/report_invoice.xml
odoo/addons/account_invoice_discount_display_amount/static/description/icon.png
odoo/addons/account_invoice_discount_display_amount/static/description/index.html
odoo/addons/account_invoice_discount_display_amount/tests/__init__.py
odoo/addons/account_invoice_discount_display_amount/tests/test_invoice_discount_display_amount.py
odoo/addons/account_invoice_discount_display_amount/views/account_move_views.xml
odoo14_addon_account_invoice_discount_display_amount-14.0.1.0.1.dev7.dist-info/METADATA
odoo14_addon_account_invoice_discount_display_amount-14.0.1.0.1.dev7.dist-info/WHEEL
odoo14_addon_account_invoice_discount_display_amount-14.0.1.0.1.dev7.dist-info/top_level.txt
odoo14_addon_account_invoice_discount_display_amount-14.0.1.0.1.dev7.dist-info/RECORD
