Metadata-Version: 2.1
Name: odoo14-addon-account_invoice_discount_display_amount
Version: 14.0.1.0.1.dev7
Summary: Show total discount applied and total without discount on invoices.
Home-page: https://github.com/OCA/account-invoicing
Author: Sygel,Odoo Community Association (OCA)
Author-email: support@odoo-community.org
License: AGPL-3
Classifier: Programming Language :: Python
Classifier: Framework :: Odoo
Classifier: Framework :: Odoo :: 14.0
Classifier: License :: OSI Approved :: GNU Affero General Public License v3
Requires-Python: >=3.6
Requires-Dist: odoo<14.1dev,>=14.0a
